releaseer/__init__.py
releaseer/app.py
releaseer/data.py
releaseer-0.7.0.dist-info/LICENSE
releaseer-0.7.0.dist-info/METADATA
releaseer-0.7.0.dist-info/WHEEL
releaseer-0.7.0.dist-info/top_level.txt
releaseer-0.7.0.dist-info/RECORD
