Metadata-Version: 2.2
Name: releaseer
Version: 0.7.0
Summary: Add your description here
Requires-Python: >=3.9
License-File: LICENSE
Requires-Dist: litestar[standard]>=2.11.0
Requires-Dist: pydantic>=2.9.0
